micro_features_cpp.abi3.so
pymicro_features/__init__.py
pymicro_features-2.0.2.dist-info/METADATA
pymicro_features-2.0.2.dist-info/WHEEL
pymicro_features-2.0.2.dist-info/top_level.txt
pymicro_features-2.0.2.dist-info/RECORD
pymicro_features-2.0.2.dist-info/licenses/LICENSE
