Metadata-Version: 2.4
Name: pymicro-features
Version: 2.0.2
Summary: Speech features using TFLite Micro audio frontend
Home-page: https://github.com/rhasspy/pymicro-features
Author: Michael Hansen
Author-email: mike@rhasspy.org
License: Apache
Requires-Python: >=3.9
License-File: LICENSE
Provides-Extra: dev
Requires-Dist: black; extra == "dev"
Requires-Dist: flake8; extra == "dev"
Requires-Dist: isort; extra == "dev"
Requires-Dist: mypy; extra == "dev"
Requires-Dist: pylint; extra == "dev"
Requires-Dist: pytest; extra == "dev"
Requires-Dist: build; extra == "dev"
Requires-Dist: syrupy; extra == "dev"
Dynamic: license-file
Dynamic: provides-extra
